qandaxfmrartifact/QandaTransformersModelArtifact.py
qandaxfmrartifact/__init__.py
qandaxfmrartifact-0.0.10.dist-info/METADATA
qandaxfmrartifact-0.0.10.dist-info/WHEEL
qandaxfmrartifact-0.0.10.dist-info/top_level.txt
qandaxfmrartifact-0.0.10.dist-info/RECORD
