Metadata-Version: 2.1
Name: qandaxfmrartifact
Version: 0.0.10
Summary: BentoML artifact framework for Q&A Transformers
Home-page: https://github.com/markmo/qandaxfmrartifact
Author: Mark Moloney
Author-email: m4rkmo@gmail.com
License: UNKNOWN
Platform: UNKNOWN
Classifier: Programming Language :: Python :: 3
Classifier: License :: OSI Approved :: MIT License
Classifier: Operating System :: OS Independent
Requires-Python: >=3.6
